Metadata-Version: 2.1
Name: garpix-htmlmin
Version: 1.1.1
Home-page: https://github.com/garpixcms/django-htmlmin
Author: Garpix LTD
Author-email: info@garpix.com
License: MIT
Classifier: Development Status :: 4 - Beta
Classifier: Environment :: Web Environment
Classifier: Intended Audience :: Developers
Classifier: License :: OSI Approved :: MIT License
Classifier: Operating System :: OS Independent
Classifier: Programming Language :: Python
Classifier: Framework :: Django
Classifier: Programming Language :: Python :: 3.8
Requires-Dist: beautifulsoup4
Requires-Dist: html5lib
